vixlib/__init__.py
vixlib/vegetationindex.py
vegbox-0.0.1.dist-info/LICENSE.txt
vegbox-0.0.1.dist-info/METADATA
vegbox-0.0.1.dist-info/WHEEL
vegbox-0.0.1.dist-info/top_level.txt
vegbox-0.0.1.dist-info/RECORD
