Metadata-Version: 2.1
Name: vegbox
Version: 0.0.1
Summary: vegbox is a powerful Python library designed for calculating and analyzing vegetation indices from remote sensing and spectral data.
Author: Radhwane Derraz
Author-email: Derraz Radhwane <derrazradhwane@gmail.com>
Project-URL: Homepage, https://www.linkedin.com/in/derraz-radhwane-phd-60649022a/
Project-URL: Issues, https://www.linkedin.com/in/derraz-radhwane-phd-60649022a/
Classifier: Programming Language :: Python :: 3
Classifier: License :: OSI Approved :: MIT License
Classifier: Operating System :: OS Independent
Requires-Python: >=3.8
License-File: LICENSE.txt
